{
  "intents": [
    {
      "id": "pointscbtcfail1_initial_question",
      "name": "Initial Question",
      "question": "\n\n      What were the events leading up to the failure?",
      "on_yes": "are_points_failing_both_N_and_R",
      "on_no": null
    },
    {
      "id": "pointscbtcfail1_smc1a",
      "name": "SMC Alarm",
      "on_yes": "legacy",
      "on_no": "outside",
      "question": "\n\n      Do you have an SMC alarm showing points disturbed?\n\n"
    },
    {
      "id": "pointscbtcfail1_smc1a",
      "name": "SMC Alarm",
      "on_yes": "legacy",
      "on_no": "outside",
      "question": "\n\n      Do you understand the series of events leading up to the failure \n      and most importantly which way the points is failing?\n\n"
    },
    {
      "id": "pointscbtcfail1_smc1b",
      "name": "SMC Alarm",
      "on_yes": "legacy",
      "on_no": "outside",
      "question": "\n\n      Is the points failing Normal to Reverse?\n\n"
    },
    {
      "id": "pointscbtcfail1_smc1b",
      "name": "SMC Alarm",
      "on_yes": "legacy",
      "on_no": "outside",
      "question": "\n\n      Is the points failing Reverse to Normal?\n\n"
    },
    {
      "id": "pointscbtcfail1_smc1b",
      "name": "SMC Alarm",
      "on_yes": "legacy",
      "on_no": "outside",
      "question": "\n\n      Stop the print train on CCOT and PG the points using PG1 SW1 [ptmne1]. \n\n      Have you confirmed point status?\n\n"
    },
    {
      "id": "pointscbtcfail1_smc1b",
      "name": "SMC Alarm",
      "on_yes": "legacy",
      "on_no": "outside",
      "question": "\n\n      Have you contacted DSIM and APCC to report point failure?\n\n"
    },
    {
      "id": "pointscbtcfail1_smc1b",
      "name": "SMC Alarm",
      "on_yes": "legacy",
      "on_no": "outside",
      "question": "\n\n      Have you contacted Service Manager, Controller and Signaller to get permission to Swing points via CCOT?\n\n"
    },
    {
      "id": "pointscbtcfail1_smc1b",
      "name": "SMC Alarm",
      "on_yes": "legacy",
      "on_no": "outside",
      "question": "\n\n      Permission granted use SP command to try clear fault?\n\n"
    },
    {
      "id": "pointscbtcfail1_smc1b",
      "name": "SMC Alarm",
      "on_yes": "legacy",
      "on_no": "outside",
      "question": "\n\n      Did fault clear using SP command?\n\n"
    },
    {
      "id": "pointscbtcfail1_smc1b",
      "name": "SMC Alarm",
      "on_yes": "legacy",
      "on_no": "outside",
      "question": "\n\n      Are points failing both N-R and R-N?\n\n"
    },
    {
      "id": "pointscbtcfail1_smc1b",
      "name": "SMC Alarm",
      "on_yes": "legacy",
      "on_no": "outside",
      "question": "\n\n      Has T.O. arrived on site and investigating point failure?\n\n"
    },
    {
      "id": "pointscbtcfail1_smc1b",
      "name": "SMC Alarm",
      "on_yes": "legacy",
      "on_no": "outside",
      "question": "\n\n      Have you got the prints?\n\n"
    },
    {
      "id": "pointscbtcfail1_smc1b",
      "name": "SMC Alarm",
      "on_yes": "legacy",
      "on_no": "outside",
      "question": "\n\n      ?\n\n"
    },
    {
      "id": "pointscbtcfail1_are_points_failing_both_N_and_R",
      "name": "Are the points failing both N and R?",
      "question": "\n\n      Are the points failing both N and R?",
      "on_yes": "test_common_og_WK_feed",
      "on_no": "suspect_common_wiring_good"
    },
    {
      "id": "pointscbtcfail1_suspect_common_wiring_good",
      "name": "Suspect Common Wiring is Good",
      "question": "\n\n      Suspect that the common wiring is good (unless there is more than one fault).",
      "on_yes": "test_common_og_WK_feed",
      "on_no": null
    },
    {
      "id": "pointscbtcfail1_test_common_og_WK_feed",
      "name": "Test the common o/g WK feed",
      "question": "\n\n      Test the common o/g WK feed. 0v chase back. 50v the fault is outside.",
      "on_yes": "chase_missing_input",
      "on_no": "fault_outside_common_wiring"
    },
    {
      "id": "pointscbtcfail1_fault_outside_common_wiring",
      "name": "Fault Outside Common Wiring",
      "question": "\n\n      The fault is outside.",
      "on_yes": null,
      "on_no": null
    },
    {
      "id": "pointscbtcfail1_chase_missing_input",
      "name": "Chase Missing Input",
      "question": "\n\n      Chase the missing input to the affected Intersig.",
      "on_yes": "does_fault_clear_with_intersig_changeover",
      "on_no": null
    },
    {
      "id": "pointscbtcfail1_does_fault_clear_with_intersig_changeover",
      "name": "Does Fault Clear with Intersig Changeover?",
      "question": "\n\n      Does the fault clear with an Intersig changeover?",
      "on_yes": "flowchart_assumes_points_failing_from_N_to_R",
      "on_no": "test_wiring_common_to_both_Intersigs"
    },
    {
      "id": "pointscbtcfail1_test_wiring_common_to_both_Intersigs",
      "name": "Test Wiring Common to Both Intersigs",
      "question": "\n\n      Test wiring that is common to both Intersigs.",
      "on_yes": null,
      "on_no": "flowchart_assumes_points_failing_from_N_to_R"
    },
    {
      "id": "pointscbtcfail1_flowchart_assumes_points_failing_from_N_to_R",
      "name": "Flowchart Assumes Points Failing from N to R",
      "question": "\n\n      Flowchart now assumes points are failing from N to R.",
      "on_yes": "has_the_RLR_latched",
      "on_no": null
    },
    {
      "id": "pointscbtcfail1_has_the_RLR_latched",
      "name": "Has the RLR Latched?",
      "question": "\n\n      Has the RLR latched?",
      "on_yes": "which_LED_is_alight_on_incoming_WK_surge_suppressors",
      "on_no": "ensure_NLR_has_unlatched_then_test_RLR_pick_up"
    },
    {
      "id": "pointscbtcfail1_ensure_NLR_has_unlatched_then_test_RLR_pick_up",
      "name": "Ensure NLR has Unlatched then Test RLR Pick Up",
      "question": "\n\n      Ensure the NLR has unlatched then test the RLR pick up.",
      "on_yes": null,
      "on_no": null
    },
    {
      "id": "pointscbtcfail1_which_LED_is_alight_on_incoming_WK_surge_suppressors",
      "name": "Which LED is Alight on Incoming WK Surge Suppressors?",
      "question": "\n\n      Which LED is alight on the incoming WK surge suppressors? None or N?",
      "on_yes": "drop_WL_using_og_WL_MCB",
      "on_no": "test_og_WL_feed"
    },
    {
      "id": "pointscbtcfail1_test_og_WL_feed",
      "name": "Test the o/g WL Feed",
      "question": "\n\n      Test the o/g WL feed. 0v chase back. 100v fault outside.",
      "on_yes": "test_og_RW_MCBs",
      "on_no": "replace_WL_MCB_points_remained_N"
    },
    {
      "id": "pointscbtcfail1_replace_WL_MCB_points_remained_N",
      "name": "Replace WL MCB, Points Remained N",
      "question": "\n\n      The points have remained N. Replace the WL MCB.",
      "on_yes": null,
      "on_no": null
    },
    {
      "id": "pointscbtcfail1_test_og_RW_MCBs",
      "name": "Test the o/g RW MCB's",
      "question": "\n\n      Test the o/g RW MCB's. 0v chase back. 100v the fault is outside.",
      "on_yes": "drop_WL_using_og_WL_MCB",
      "on_no": "points_have_not_achieved_R_detection"
    },
    {
      "id": "pointscbtcfail1_points_have_not_achieved_R_detection",
      "name": "The points have not achieved R detection.",
      "question": "\n\n      The points have not achieved R detection.",
      "on_yes": "drop_WL_using_og_WL_MCB",
      "on_no": null
    },
    {
      "id": "pointscbtcfail1_drop_WL_using_og_WL_MCB",
      "name": "Drop the WL using the o/g WL MCB.",
      "question": "\n\n      Drop the WL using the o/g WL MCB. Does the LED alight on the N WK surge suppressor?",
      "on_yes": "test_incoming_N_WK_MCBs",
      "on_no": null
    },
    {
      "id": "pointscbtcfail1_test_incoming_N_WK_MCBs",
      "name": "Test incoming N WK MCB's",
      "question": "\n\n      Test incoming N WK MCB's. The points have moved from N. Replace the WL MCB. 0v The fault is outside.",
      "on_yes": null,
      "on_no": null
    }
  ]
}
